odoo8_addon_base_vat_ar-8.0.1.0.0.99.dev4-nspkg.pth
odoo_addons/base_vat_ar/AUTHORS
odoo_addons/base_vat_ar/__init__.py
odoo_addons/base_vat_ar/__openerp__.py
odoo_addons/base_vat_ar/partner.py
odoo_addons/base_vat_ar/partner_data.xml
odoo_addons/base_vat_ar/partner_view.xml
odoo_addons/base_vat_ar/i18n/es.mo
odoo_addons/base_vat_ar/i18n/es.po
odoo_addons/base_vat_ar/security/ir.model.access.csv
odoo_addons/base_vat_ar/static/description/icon.png
odoo8_addon_base_vat_ar-8.0.1.0.0.99.dev4.dist-info/METADATA
odoo8_addon_base_vat_ar-8.0.1.0.0.99.dev4.dist-info/WHEEL
odoo8_addon_base_vat_ar-8.0.1.0.0.99.dev4.dist-info/namespace_packages.txt
odoo8_addon_base_vat_ar-8.0.1.0.0.99.dev4.dist-info/top_level.txt
odoo8_addon_base_vat_ar-8.0.1.0.0.99.dev4.dist-info/RECORD
